project_26.srcs/sources_1/new/beat.v
`timescale 1ns / 1ps

// ------------------- RAM Module -------------------
module ram(
    input clk,
    input we,
    input rst,
    input [5:0] addr,
    input [7:0] din,
    output reg [7:0] dout
);
    reg [7:0] mem [63:0];

    initial begin
        mem[0] = 8'd85;  // IBI1 = 850ms
        mem[1] = 8'd86;  // IBI2 = 860ms
        mem[2] = 8'd94;
        mem[3] = 8'd78;
    end

    always @(posedge clk) begin
        if (rst)
            dout <= 8'h00;
        else if (we)
            mem[addr] <= din;
        else
            dout <= mem[addr];
    end
endmodule


// ------------------- Pipelined ALU -------------------
module pipelined_alu (
    input wire clk,
    input wire rst,
    input wire [7:0] a, b,
    input wire [1:0] opcode,
    output reg [7:0] result,
    output reg flag
);
    localparam OP_BPM = 2'b00,
               OP_HRV = 2'b01,
               OP_AVG = 2'b10,
               OP_IRR = 2'b11;

    reg [7:0] a_reg, b_reg;
    reg [1:0] opcode_reg;
    reg [7:0] alu_result_stage2;
    reg flag_stage2;
    reg [7:0] diff, temp;

    // Stage 1
    always @(posedge clk or posedge rst) begin
        if (rst) begin
            a_reg <= 0; b_reg <= 0; opcode_reg <= 0;
        end else begin
            a_reg <= a;
            b_reg <= b;
            opcode_reg <= opcode;
        end
    end

    // Stage 2
    always @(posedge clk or posedge rst) begin
        if (rst) begin
            alu_result_stage2 <= 0;
            flag_stage2 <= 0;
        end else begin
            case (opcode_reg)
                OP_BPM: begin
                    if (a_reg != 0) begin
                        alu_result_stage2 <= 6000 / a_reg;
                        flag_stage2 <= (6000 / a_reg < 50 || 6000 / a_reg > 100);
                    end else begin
                        alu_result_stage2 <= 0;
                        flag_stage2 <= 1;
                    end
                end
                OP_HRV: begin
                    temp = (a_reg > b_reg) ? (a_reg - b_reg) : (b_reg - a_reg);
                    alu_result_stage2 <= temp;
                    flag_stage2 <= (temp < 8);
                end
                OP_AVG: begin
                    alu_result_stage2 <= (a_reg + b_reg) >> 1;
                    flag_stage2 <= 0;
                end
                OP_IRR: begin
                    diff = (a_reg > b_reg) ? (a_reg - b_reg) : (b_reg - a_reg);
                    alu_result_stage2 <= diff;
                    flag_stage2 <= (diff > 15);
                end
                default: begin
                    alu_result_stage2 <= 0;
                    flag_stage2 <= 0;
                end
            endcase
        end
    end

    // Stage 3
    always @(posedge clk or posedge rst) begin
        if (rst) begin
            result <= 0;
            flag <= 0;
        end else begin
            result <= alu_result_stage2;
            flag <= flag_stage2;
        end
    end
endmodule


// ------------------- Interrupt Controller -------------------
module interrupt_controller(
    input wire ext_int,
    input wire int_int,
    output reg [1:0] irq_vector,
    output reg irq_valid
);
    always @(*) begin
        if (ext_int) begin
            irq_vector = 2'b01;
            irq_valid = 1;
        end else if (int_int) begin
            irq_vector = 2'b10;
            irq_valid = 1;
        end else begin
            irq_vector = 2'b00;
            irq_valid = 0;
        end
    end
endmodule


// ------------------- FSM with Latched Interrupt Logic -------------------
module beat(
    input clk,
    input rst,
    input ext_int,
    input int_int,
    output [4:0] state_out,
    output fsm_busy_out,
    output interrupt_pending_out,
    output [1:0] irq_vector_out,
    output reg [7:0] bpm, hrv, avg, irr,
    output reg done
);
    reg [4:0] state, saved_state;
    reg [5:0] addr, index;
    reg [7:0] a, b;
    reg [1:0] opcode;
    reg [7:0] alu_a, alu_b;
    reg we = 0;
    reg fsm_busy;
    reg interrupt_pending;
    reg [1:0] active_irq_vector;
    reg interrupt_pending_ext, interrupt_pending_int;

    wire [7:0] ram_dout;
    wire [7:0] alu_result;
    wire alu_flag;
    wire [1:0] irq_vector;
    wire irq_valid;

    ram mem_inst (
        .clk(clk), .we(we), .rst(rst), .addr(addr), .din(8'd0), .dout(ram_dout)
    );

    pipelined_alu alu_inst (
        .clk(clk), .rst(rst), .a(alu_a), .b(alu_b), .opcode(opcode), .result(alu_result), .flag(alu_flag)
    );

    interrupt_controller irq_ctrl (
        .ext_int(ext_int), .int_int(int_int), .irq_vector(irq_vector), .irq_valid(irq_valid)
    );

    always @(posedge clk or posedge rst) begin
        if (rst) begin
            state <= 0; addr <= 0; index <= 0;
            a <= 0; b <= 0; opcode <= 0; alu_a <= 0; alu_b <= 0;
            bpm <= 0; hrv <= 0; avg <= 0; irr <= 0;
            fsm_busy <= 0; interrupt_pending <= 0; done <= 0;
            interrupt_pending_ext <= 0; interrupt_pending_int <= 0;
        end else begin
            // Latch interrupts
            if (ext_int) interrupt_pending_ext <= 1;
            if (int_int) interrupt_pending_int <= 1;

            if (!interrupt_pending && !fsm_busy && (interrupt_pending_ext || interrupt_pending_int)) begin
                interrupt_pending <= 1;
                saved_state <= state;
                if (interrupt_pending_ext) begin
                    active_irq_vector <= 2'b01;
                    state <= 5'd30;
                end else if (interrupt_pending_int) begin
                    active_irq_vector <= 2'b10;
                    state <= 5'd31;
                end
            end else begin
                case (state)
                    5'd0: begin addr <= index; state <= 1; irr <= alu_result; fsm_busy <= 0; end
                    5'd1: state <= 2;
                    5'd2: begin a <= ram_dout; addr <= index + 1; state <= 3; end
                    5'd3: state <= 4;
                    5'd4: begin b <= ram_dout; state <= 5; end
                    5'd5: begin opcode <= 2'b00; alu_a <= a; alu_b <= b; fsm_busy <= 1; state <= 6; end
                    5'd6: state <= 7;
                    5'd7: state <= 8;
                    5'd8: begin opcode <= 2'b01; alu_a <= a; alu_b <= b; state <= 9; end
                    5'd9: state <= 10;
                    5'd10: begin bpm <= alu_result; state <= 11; end
                    5'd11: begin opcode <= 2'b10; alu_a <= a; alu_b <= b; state <= 12; end
                    5'd12: state <= 13;
                    5'd13: begin hrv <= alu_result; state <= 14; end
                    5'd14: begin opcode <= 2'b11; alu_a <= a; alu_b <= b; state <= 15; end
                    5'd15: state <= 16;
                    5'd16: begin avg <= alu_result; state <= 17; end
                    5'd17: begin
                        if (index >= 6'd3) begin done <= 1; state <= 17;
                        end else begin index <= index + 2; state <= 0; end
                    end
                    5'd30: begin bpm <= 0; interrupt_pending <= 0; interrupt_pending_ext <= 0; state <= saved_state; end
                    5'd31: begin hrv <= hrv + 1; interrupt_pending <= 0; interrupt_pending_int <= 0; state <= saved_state; end
                endcase
            end
        end
    end

    assign state_out = state;
    assign fsm_busy_out = fsm_busy;
    assign interrupt_pending_out = interrupt_pending;
    assign irq_vector_out = irq_vector;

endmodule

project_26.srcs/sim_1/new/tb_beat.v
`timescale 1ns / 1ps

module beat_tb;

    reg clk = 0;
    reg rst = 1;
    reg ext_int = 0;
    reg int_int = 0;

    wire [7:0] bpm, hrv, avg, irr;
    wire done;
    wire [4:0] state_out;
    wire fsm_busy_out;
    wire interrupt_pending_out;
    wire [1:0] irq_vector_out;

    // Clock generation: 10ns period (100MHz)
    always #5 clk = ~clk;

    // DUT instance
    beat uut (
        .clk(clk),
        .rst(rst),
        .ext_int(ext_int),
        .int_int(int_int),
        .bpm(bpm),
        .hrv(hrv),
        .avg(avg),
        .irr(irr),
        .done(done),
        .state_out(state_out),
        .fsm_busy_out(fsm_busy_out),
        .interrupt_pending_out(interrupt_pending_out),
        .irq_vector_out(irq_vector_out)
    );

    initial begin
        $display("Starting simulation...");
        $dumpfile("beat_tb.vcd");     // For GTKWave
        $dumpvars(0, beat_tb);

        // Reset
        #20 rst = 0;

        // Let FSM operate a bit
        #380;

        // Trigger external interrupt (bpm reset)
        $display(">>> External interrupt triggered at %t", $time);
        ext_int = 1;
        #10;
        ext_int = 0;

        // Wait more and trigger internal interrupt (hrv increment)
        #0;
        $display(">>> Internal interrupt triggered at %t", $time);
        int_int = 1;
        #10;
        int_int = 0;

        // Wait for FSM to finish
        #300;

        $display("Final BPM = %d", bpm);
        $display("Final HRV = %d", hrv);
        $display("Final AVG = %d", avg);
        $display("Final IRR = %d", irr);

        $finish;
    end

endmodule

project_26.sim/sim_1/behav/xsim/beat_tb.vcd
$date
   Sat Aug  2 18:50:15 2025
$end
$version
  2020.2
$end
$timescale
  1ps
$end
$scope module beat_tb $end
$var reg 1 ! clk $end
$var reg 1 " rst $end
$var reg 1 # ext_int $end
$var reg 1 $ int_int $end
$var wire 8 % bpm [7:0] $end
$var wire 8 & hrv [7:0] $end
$var wire 8 ' avg [7:0] $end
$var wire 8 ( irr [7:0] $end
$var wire 1 ) done $end
$var wire 5 * state_out [4:0] $end
$var wire 1 + fsm_busy_out $end
$var wire 1 , interrupt_pending_out $end
$var wire 2 - irq_vector_out [1:0] $end
$scope module uut $end
$var wire 1 . clk $end
$var wire 1 / rst $end
$var wire 1 0 ext_int $end
$var wire 1 1 int_int $end
$var wire 5 * state_out [4:0] $end
$var wire 1 + fsm_busy_out $end
$var wire 1 , interrupt_pending_out $end
$var wire 2 - irq_vector_out [1:0] $end
$var reg 8 2 bpm [7:0] $end
$var reg 8 3 hrv [7:0] $end
$var reg 8 4 avg [7:0] $end
$var reg 8 5 irr [7:0] $end
$var reg 1 6 done $end
$var reg 5 7 state [4:0] $end
$var reg 5 8 saved_state [4:0] $end
$var reg 6 9 addr [5:0] $end
$var reg 6 : index [5:0] $end
$var reg 8 ; a [7:0] $end
$var reg 8 < b [7:0] $end
$var reg 2 = opcode [1:0] $end
$var reg 8 > alu_a [7:0] $end
$var reg 8 ? alu_b [7:0] $end
$var reg 1 @ we $end
$var reg 1 A fsm_busy $end
$var reg 1 B interrupt_pending $end
$var reg 2 C active_irq_vector [1:0] $end
$var reg 1 D interrupt_pending_ext $end
$var reg 1 E interrupt_pending_int $end
$var wire 8 F ram_dout [7:0] $end
$var wire 8 G alu_result [7:0] $end
$var wire 1 H alu_flag $end
$var wire 2 I irq_vector [1:0] $end
$var wire 1 J irq_valid $end
$scope module mem_inst $end
$var wire 1 . clk $end
$var wire 1 K we $end
$var wire 1 / rst $end
$var wire 6 L addr [5:0] $end
$var wire 8 M din [7:0] $end
$var reg 8 N dout [7:0] $end
$upscope $end
$scope module alu_inst $end
$var wire 1 . clk $end
$var wire 1 / rst $end
$var wire 8 O a [7:0] $end
$var wire 8 P b [7:0] $end
$var wire 2 Q opcode [1:0] $end
$var reg 8 R result [7:0] $end
$var reg 1 S flag $end
$var reg 8 T a_reg [7:0] $end
$var reg 8 U b_reg [7:0] $end
$var reg 2 V opcode_reg [1:0] $end
$var reg 8 W alu_result_stage2 [7:0] $end
$var reg 1 X flag_stage2 $end
$var reg 8 Y diff [7:0] $end
$var reg 8 Z temp [7:0] $end
$var parameter 2 [ OP_BPM [1:0] $end
$var parameter 2 \ OP_HRV [1:0] $end
$var parameter 2 ] OP_AVG [1:0] $end
$var parameter 2 ^ OP_IRR [1:0] $end
$upscope $end
$scope module irq_ctrl $end
$var wire 1 0 ext_int $end
$var wire 1 1 int_int $end
$var reg 2 _ irq_vector [1:0] $end
$var reg 1 ` irq_valid $end
$upscope $end
$upscope $end
$upscope $end
$enddefinitions $end
#0
$dumpvars
0!
1"
0#
0$
b0 %
b0 &
b0 '
b0 (
0)
b0 *
0+
0,
b0 -
0.
1/
00
01
b0 2
b0 3
b0 4
b0 5
06
b0 7
bx 8
b0 9
b0 :
b0 ;
b0 <
b0 =
b0 >
b0 ?
0@
0A
0B
bx C
0D
0E
bx F
b0 G
0H
b0 I
0J
0K
b0 L
b0 M
bx N
b0 O
b0 P
b0 Q
b0 R
0S
b0 T
b0 U
b0 V
b0 W
0X
bx Y
bx Z
b0 [
b1 \
b10 ]
b11 ^
b0 _
0`
$end
#5000
1!
1.
b0 F
b0 N
#10000
0!
0.
#15000
1!
1.
#20000
0!
0"
0.
0/
#25000
1!
b1 *
1.
b1 7
b1010101 F
b1010101 N
1X
#30000
0!
0.
#35000
1!
b10 *
1.
b10 7
1H
1S
#40000
0!
0.
#45000
1!
b11 *
1.
b11 7
b1 9
b1010101 ;
b1 L
#50000
0!
0.
#55000
1!
b100 *
1.
b100 7
b1010110 F
b1010110 N
#60000
0!
0.
#65000
1!
b101 *
1.
b101 7
b1010110 <
#70000
0!
0.
#75000
1!
b110 *
1+
1.
b110 7
b1010101 >
b1010110 ?
1A
b1010101 O
b1010110 P
#80000
0!
0.
#85000
1!
b111 *
1.
b111 7
b1010101 T
b1010110 U
#90000
0!
0.
#95000
1!
b1000 *
1.
b1000 7
b1000110 W
0X
#100000
0!
0.
#105000
1!
b1001 *
1.
b1001 7
b1 =
b1000110 G
0H
b1 Q
b1000110 R
0S
#110000
0!
0.
#115000
1!
b1010 *
1.
b1010 7
b1 V
#120000
0!
0.
#125000
1!
b1000110 %
b1011 *
1.
b1000110 2
b1011 7
b1 W
1X
b1 Z
#130000
0!
0.
#135000
1!
b1100 *
1.
b1100 7
b10 =
b1 G
1H
b10 Q
b1 R
1S
#140000
0!
0.
#145000
1!
b1101 *
1.
b1101 7
b10 V
#150000
0!
0.
#155000
1!
b1 &
b1110 *
1.
b1 3
b1110 7
b1010101 W
0X
#160000
0!
0.
#165000
1!
b1111 *
1.
b1111 7
b11 =
b1010101 G
0H
b11 Q
b1010101 R
0S
#170000
0!
0.
#175000
1!
b10000 *
1.
b10000 7
b11 V
#180000
0!
0.
#185000
1!
b1010101 '
b10001 *
1.
b1010101 4
b10001 7
b1 W
b1 Y
#190000
0!
0.
#195000
1!
b0 *
1.
b0 7
b10 :
b1 G
b1 R
#200000
0!
0.
#205000
1!
b1 (
b1 *
0+
1.
b1 5
b1 7
b10 9
0A
b10 L
#210000
0!
0.
#215000
1!
b10 *
1.
b10 7
b1011110 F
b1011110 N
#220000
0!
0.
#225000
1!
b11 *
1.
b11 7
b11 9
b1011110 ;
b11 L
#230000
0!
0.
#235000
1!
b100 *
1.
b100 7
b1001110 F
b1001110 N
#240000
0!
0.
#245000
1!
b101 *
1.
b101 7
b1001110 <
#250000
0!
0.
#255000
1!
b110 *
1+
1.
b110 7
b0 =
b1011110 >
b1001110 ?
1A
b1011110 O
b1001110 P
b0 Q
#260000
0!
0.
#265000
1!
b111 *
1.
b111 7
b1011110 T
b1001110 U
b0 V
#270000
0!
0.
#275000
1!
b1000 *
1.
b1000 7
b111111 W
#280000
0!
0.
#285000
1!
b1001 *
1.
b1001 7
b1 =
b111111 G
b1 Q
b111111 R
#290000
0!
0.
#295000
1!
b1010 *
1.
b1010 7
b1 V
#300000
0!
0.
#305000
1!
b111111 %
b1011 *
1.
b111111 2
b1011 7
b10000 W
b10000 Z
#310000
0!
0.
#315000
1!
b1100 *
1.
b1100 7
b10 =
b10000 G
b10 Q
b10000 R
#320000
0!
0.
#325000
1!
b1101 *
1.
b1101 7
b10 V
#330000
0!
0.
#335000
1!
b10000 &
b1110 *
1.
b10000 3
b1110 7
b1010110 W
#340000
0!
0.
#345000
1!
b1111 *
1.
b1111 7
b11 =
b1010110 G
b11 Q
b1010110 R
#350000
0!
0.
#355000
1!
b10000 *
1.
b10000 7
b11 V
#360000
0!
0.
#365000
1!
b1010110 '
b10001 *
1.
b1010110 4
b10001 7
b10000 W
1X
b10000 Y
#370000
0!
0.
#375000
1!
b0 *
1.
b0 7
b100 :
b10000 G
1H
b10000 R
1S
#380000
0!
0.
#385000
1!
b10000 (
b1 *
0+
1.
b10000 5
b1 7
b100 9
0A
b100 L
#390000
0!
0.
#395000
1!
b10 *
1.
b10 7
bx F
bx N
#400000
0!
1#
b1 -
0.
10
b1 I
1J
b1 _
1`
#405000
1!
b11 *
1.
b11 7
b101 9
bx ;
1D
b101 L
#410000
0!
0#
1$
b10 -
0.
00
11
b10 I
1J
b10 _
1`
#415000
1!
b11110 *
1,
1.
b11110 7
b11 8
1B
b1 C
1E
#420000
0!
0$
b0 -
0.
01
b0 I
0J
b0 _
0`
#425000
1!
b0 %
b11 *
0,
1.
b0 2
b11 7
0B
0D
#430000
0!
0.
#435000
1!
b11111 *
1,
1.
b11111 7
1B
b10 C
#440000
0!
0.
#445000
1!
b10001 &
b11 *
0,
1.
b10001 3
b11 7
0B
0E
#450000
0!
0.
#455000
1!
b100 *
1.
b100 7
#460000
0!
0.
#465000
1!
b101 *
1.
b101 7
bx <
#470000
0!
0.
#475000
1!
b110 *
1+
1.
b110 7
b0 =
bx >
bx ?
1A
bx O
bx P
b0 Q
#480000
0!
0.
#485000
1!
b111 *
1.
b111 7
bx T
bx U
b0 V
#490000
0!
0.
#495000
1!
b1000 *
1.
b1000 7
b0 W
#500000
0!
0.
#505000
1!
b1001 *
1.
b1001 7
b1 =
b0 G
b1 Q
b0 R
#510000
0!
0.
#515000
1!
b1010 *
1.
b1010 7
b1 V
#520000
0!
0.
#525000
1!
b1011 *
1.
b1011 7
bx W
xX
bx Z
#530000
0!
0.
#535000
1!
b1100 *
1.
b1100 7
b10 =
bx G
xH
b10 Q
bx R
xS
#540000
0!
0.
#545000
1!
b1101 *
1.
b1101 7
b10 V
#550000
0!
0.
#555000
1!
bx &
b1110 *
1.
bx 3
b1110 7
b0xxxxxxx W
0X
#560000
0!
0.
#565000
1!
b1111 *
1.
b1111 7
b11 =
b0xxxxxxx G
0H
b11 Q
b0xxxxxxx R
0S
#570000
0!
0.
#575000
1!
b10000 *
1.
b10000 7
b11 V
#580000
0!
0.
#585000
1!
b0xxxxxxx '
b10001 *
1.
b0xxxxxxx 4
b10001 7
bx W
xX
bx Y
#590000
0!
0.
#595000
1!
1)
1.
16
bx G
xH
bx R
xS
